repo_serializer/__init__.py
repo_serializer/cli.py
repo_serializer/config.py
repo_serializer/file_processors.py
repo_serializer/filters.py
repo_serializer/prompt_extractor.py
repo_serializer/serializer.py
repo_serializer/statistics.py
repo_serializer/structure.py
repo_serializer-1.2.0.dist-info/METADATA
repo_serializer-1.2.0.dist-info/WHEEL
repo_serializer-1.2.0.dist-info/entry_points.txt
repo_serializer-1.2.0.dist-info/top_level.txt
repo_serializer-1.2.0.dist-info/RECORD
