Metadata-Version: 2.4
Name: repo-serializer
Version: 1.2.0
Summary: A tool to serialize repository contents into a single file
Home-page: https://github.com/marutilai/repo-serializer
Author: Maruti Agarwal
Author-email: marutiagarwal@gmail.com
Project-URL: Source, https://github.com/marutilai/repo-serializer
Project-URL: Bug Tracker, https://github.com/marutilai/repo-serializer/issues
Classifier: Programming Language :: Python :: 3
Classifier: License :: OSI Approved :: MIT License
Classifier: Operating System :: OS Independent
Requires-Python: >=3.10
Requires-Dist: pyperclip
Requires-Dist: pyyaml>=6.0
Provides-Extra: dev
Requires-Dist: pytest>=7.0; extra == "dev"
Dynamic: author
Dynamic: author-email
Dynamic: classifier
Dynamic: description
Dynamic: description-content-type
Dynamic: home-page
Dynamic: project-url
Dynamic: provides-extra
Dynamic: requires-dist
Dynamic: requires-python
Dynamic: summary
